depends_on/__init__.py
depends_on/ansible.py
depends_on/common.py
depends_on/golang.py
depends_on/javascript.py
depends_on/python.py
depends_on-0.15.0.data/scripts/depends_on_stage1
depends_on-0.15.0.data/scripts/depends_on_stage2
depends_on-0.15.0.data/scripts/depends_on_stage3
depends_on-0.15.0.dist-info/LICENSE
depends_on-0.15.0.dist-info/METADATA
depends_on-0.15.0.dist-info/WHEEL
depends_on-0.15.0.dist-info/top_level.txt
depends_on-0.15.0.dist-info/RECORD
