Metadata-Version: 2.1
Name: depends-on
Version: 0.15.0
Summary: A Python library to manage dependencies between changes.
Home-page: UNKNOWN
Author: The Depends-On Team
License: UNKNOWN
Platform: UNKNOWN
Classifier: Development Status :: 5 - Production/Stable
Classifier: Programming Language :: Python :: 3
Classifier: License :: OSI Approved :: GNU General Public License v3 (GPLv3)
Classifier: Topic :: Software Development :: Version Control :: Git
Classifier: Topic :: Software Development :: Testing
Classifier: Topic :: Software Development :: Quality Assurance
License-File: LICENSE
